SharkHenglingJichuPojieJiaochengZhiTuwenBan/README.md
SharkHenglingJichuPojieJiaochengZhiTuwenBan/__init__.py
SharkHenglingJichuPojieJiaochengZhiTuwenBan/__main__.py
SharkHenglingJichuPojieJiaochengZhiTuwenBan/file.epub
SharkHenglingJichuPojieJiaochengZhiTuwenBan/index.html
SharkHenglingJichuPojieJiaochengZhiTuwenBan/css/__init__.py
SharkHenglingJichuPojieJiaochengZhiTuwenBan/css/annotations.css
SharkHenglingJichuPojieJiaochengZhiTuwenBan/css/main.css
SharkHenglingJichuPojieJiaochengZhiTuwenBan/css/normalize.css
SharkHenglingJichuPojieJiaochengZhiTuwenBan/css/popup.css
SharkHenglingJichuPojieJiaochengZhiTuwenBan/font/__init__.py
SharkHenglingJichuPojieJiaochengZhiTuwenBan/font/fontello.eot
SharkHenglingJichuPojieJiaochengZhiTuwenBan/font/fontello.svg
SharkHenglingJichuPojieJiaochengZhiTuwenBan/font/fontello.ttf
SharkHenglingJichuPojieJiaochengZhiTuwenBan/font/fontello.woff
SharkHenglingJichuPojieJiaochengZhiTuwenBan/img/__init__.py
SharkHenglingJichuPojieJiaochengZhiTuwenBan/img/annotator-glyph-sprite.png
SharkHenglingJichuPojieJiaochengZhiTuwenBan/img/annotator-icon-sprite.png
SharkHenglingJichuPojieJiaochengZhiTuwenBan/img/apple-touch-icon.png
SharkHenglingJichuPojieJiaochengZhiTuwenBan/img/cancelfullscreen.png
SharkHenglingJichuPojieJiaochengZhiTuwenBan/img/close.png
SharkHenglingJichuPojieJiaochengZhiTuwenBan/img/fullscreen.png
SharkHenglingJichuPojieJiaochengZhiTuwenBan/img/loader.gif
SharkHenglingJichuPojieJiaochengZhiTuwenBan/img/menu-icon.png
SharkHenglingJichuPojieJiaochengZhiTuwenBan/img/save.png
SharkHenglingJichuPojieJiaochengZhiTuwenBan/img/saved.png
SharkHenglingJichuPojieJiaochengZhiTuwenBan/img/settings-s.png
SharkHenglingJichuPojieJiaochengZhiTuwenBan/img/settings.png
SharkHenglingJichuPojieJiaochengZhiTuwenBan/img/star.png
SharkHenglingJichuPojieJiaochengZhiTuwenBan/js/__init__.py
SharkHenglingJichuPojieJiaochengZhiTuwenBan/js/epub.js
SharkHenglingJichuPojieJiaochengZhiTuwenBan/js/epub.min.js
shark_hengling_jichu_pojie_jiaocheng_zhi_tuwen_ban-2024.3.2.0.dist-info/METADATA
shark_hengling_jichu_pojie_jiaocheng_zhi_tuwen_ban-2024.3.2.0.dist-info/WHEEL
shark_hengling_jichu_pojie_jiaocheng_zhi_tuwen_ban-2024.3.2.0.dist-info/entry_points.txt
shark_hengling_jichu_pojie_jiaocheng_zhi_tuwen_ban-2024.3.2.0.dist-info/top_level.txt
shark_hengling_jichu_pojie_jiaocheng_zhi_tuwen_ban-2024.3.2.0.dist-info/RECORD
